LabelSmoothingCrossEntropy.py
helloworld.py
pytorch_losses-0.0.1.dist-info/METADATA
pytorch_losses-0.0.1.dist-info/WHEEL
pytorch_losses-0.0.1.dist-info/top_level.txt
pytorch_losses-0.0.1.dist-info/RECORD
